ae/__init__.py
ae/defaults.py
ae/setup.py
ae/utils.py
ae/extraction/__init__.py
ae/extraction/author_extract.py
ae/extraction/content_extract.py
ae/extraction/list_page_extract.py
ae/extraction/source_extract.py
ae/extraction/time_extract.py
ae/extraction/title_extract.py
automatic_extraction-0.1.dist-info/LICENSE
automatic_extraction-0.1.dist-info/METADATA
automatic_extraction-0.1.dist-info/WHEEL
automatic_extraction-0.1.dist-info/top_level.txt
automatic_extraction-0.1.dist-info/RECORD
